hindi/__init__.py
hindi/hindi.py
hindi-0.1.dist-info/LICENSE
hindi-0.1.dist-info/METADATA
hindi-0.1.dist-info/WHEEL
hindi-0.1.dist-info/top_level.txt
hindi-0.1.dist-info/RECORD
