Metadata-Version: 2.1
Name: hindi
Version: 0.1
Summary: Hindi language utility library for Python
Author-email: setools <setools.xyz@gmail.com>
Classifier: Programming Language :: Python :: 3
Classifier: License :: OSI Approved :: MIT License
Classifier: Operating System :: OS Independent
Requires-Python: >=3.7
License-File: LICENSE
